data/nakamon_status.csv
data/orange_skill.csv
data/red_skill.csv
data/resistance_skill.csv
data/resistance_status.csv
nakamon/__init__.py
nakamon/damage.py
nakamon/nakamon.py
nakamon-0.1.0a6.dist-info/LICENSE
nakamon-0.1.0a6.dist-info/METADATA
nakamon-0.1.0a6.dist-info/WHEEL
nakamon-0.1.0a6.dist-info/RECORD
