Metadata-Version: 2.1
Name: nakamon
Version: 0.1.0a6
Summary: 
Author: driller
Requires-Python: >=3.10,<4.0
Classifier: Programming Language :: Python :: 3
Classifier: Programming Language :: Python :: 3.10
Classifier: Programming Language :: Python :: 3.11
Requires-Dist: pandas (>=2.0.3,<3.0.0)
